metamatex/grpc_sdk/__init__.py
metamatex/grpc_sdk/v2019_02/__init__.py
metamatex/grpc_sdk/v2019_02/proto2/__init__.py
metamatex/grpc_sdk/v2019_02/proto2/schema_pb2.py
metamatex/grpc_sdk/v2019_02/proto2/schema_pb2_grpc.py
metamatex.grpc_sdk-0.0.148.dist-info/LICENSE
metamatex.grpc_sdk-0.0.148.dist-info/METADATA
metamatex.grpc_sdk-0.0.148.dist-info/WHEEL
metamatex.grpc_sdk-0.0.148.dist-info/top_level.txt
metamatex.grpc_sdk-0.0.148.dist-info/RECORD
