Metadata-Version: 2.1
Name: metamatex.grpc-sdk
Version: 0.0.148
Summary: UNKNOWN
Home-page: https://github.com/metamatex/grpc-sdk
Author: UNKNOWN
Author-email: UNKNOWN
License: UNKNOWN
Platform: UNKNOWN
Requires-Dist: googleapis-common-protos
Requires-Dist: grpcio-tools
